ed_notification/__init__.py
ed_notification/application/__init__.py
ed_notification/application/common/__init__.py
ed_notification/application/common/responses/__init__.py
ed_notification/application/common/responses/base_response.py
ed_notification/application/contracts/__init__.py
ed_notification/application/contracts/infrastructure/__init__.py
ed_notification/application/features/__init__.py
ed_notification/application/features/notification/__init__.py
ed_notification/application/features/notification/dtos/__init__.py
ed_notification/application/features/notification/dtos/notification_dto.py
ed_notification/application/features/notification/dtos/send_notification_dto.py
ed_notification/application/features/notification/dtos/update_notification_dto.py
ed_notification/application/features/notification/dtos/validators/__init__.py
ed_notification/application/features/notification/handlers/__init__.py
ed_notification/application/features/notification/handlers/commands/__init__.py
ed_notification/application/features/notification/handlers/commands/send_notification_command_handler.py
ed_notification/application/features/notification/handlers/commands/update_notification_command_handler.py
ed_notification/application/features/notification/handlers/queries/__init__.py
ed_notification/application/features/notification/handlers/queries/get_notification_query_handler.py
ed_notification/application/features/notification/handlers/queries/get_notifications_query_handler.py
ed_notification/application/features/notification/requests/__init__.py
ed_notification/application/features/notification/requests/commands/__init__.py
ed_notification/application/features/notification/requests/commands/send_notification_command.py
ed_notification/application/features/notification/requests/commands/update_notification_command.py
ed_notification/application/features/notification/requests/queries/__init__.py
ed_notification-0.1.20.dist-info/licenses/LICENSE
ed_notification-0.1.20.dist-info/METADATA
ed_notification-0.1.20.dist-info/WHEEL
ed_notification-0.1.20.dist-info/top_level.txt
ed_notification-0.1.20.dist-info/RECORD
